panoptes_client/__init__.py
panoptes_client/aggregation.py
panoptes_client/caesar.py
panoptes_client/classification.py
panoptes_client/collection.py
panoptes_client/collection_role.py
panoptes_client/exportable.py
panoptes_client/inaturalist.py
panoptes_client/organization.py
panoptes_client/panoptes.py
panoptes_client/project.py
panoptes_client/project_preferences.py
panoptes_client/project_role.py
panoptes_client/set_member_subject.py
panoptes_client/subject.py
panoptes_client/subject_set.py
panoptes_client/subject_workflow_status.py
panoptes_client/user.py
panoptes_client/utils.py
panoptes_client/workflow.py
panoptes_client/workflow_version.py
panoptes_client/tests/__init__.py
panoptes_client/tests/test_bearer_expiry.py
panoptes_client/tests/test_http_retries.py
panoptes_client/tests/test_inaturalist.py
panoptes_client/tests/test_linkcollection.py
panoptes_client/tests/test_linkresolver.py
panoptes_client/tests/test_project.py
panoptes_client/tests/test_set_member_subject.py
panoptes_client/tests/test_subject.py
panoptes_client/tests/test_subject_set.py
panoptes_client/tests/test_workflow.py
panoptes_client-1.7.1.dist-info/LICENSE
panoptes_client-1.7.1.dist-info/METADATA
panoptes_client-1.7.1.dist-info/WHEEL
panoptes_client-1.7.1.dist-info/top_level.txt
panoptes_client-1.7.1.dist-info/RECORD
