Metadata-Version: 2.1
Name: panoptes-client
Version: 1.7.1
Summary: This package is the Python SDK for Panoptes, the platform behind the Zooniverse. This module is intended to allow programmatic management of projects, providing high level access to the API for common project management tasks.
Home-page: https://github.com/zooniverse/panoptes-python-client
Author: Adam McMaster / Zooniverse
Author-email: contact@zooniverse.org
License: UNKNOWN
Platform: UNKNOWN
License-File: LICENSE
Requires-Dist: requests>=2.4.2
Requires-Dist: future>=0.16
Requires-Dist: python-magic>=0.4
Requires-Dist: redo>=1.7
Requires-Dist: six>=1.9
Requires-Dist: futures; python_version == "2.7"
Provides-Extra: docs
Requires-Dist: sphinx; extra == "docs"
Provides-Extra: testing
Requires-Dist: mock>=2.0; extra == "testing"
